{"directed": false, "multigraph": false, "graph": {}, "nodes": [{"log_enabled": true, "log_dir": "/home/p4/projekt/network_telemetry/src/log", "cls": null, "isHost": true, "mac": "00:00:0a:00:00:01", "ip": "10.0.0.1/16", "id": "h1"}, {"log_enabled": true, "log_dir": "/home/p4/projekt/network_telemetry/src/log", "cls": null, "isHost": true, "mac": "00:00:0a:00:00:02", "ip": "10.0.0.2/16", "id": "h2"}, {"p4_src": "p4src.p4", "pcap_dump": true, "pcap_dir": "/home/p4/projekt/network_telemetry/src/pcap", "log_enabled": true, "log_dir": "/home/p4/projekt/network_telemetry/src/log", "cls": null, "cli_input": "s1-commands.txt", "isP4Switch": true, "isSwitch": true, "device_id": 1, "thrift_port": 9090, "json_path": "/home/p4/projekt/network_telemetry/src/p4src.json", "id": "s1"}, {"p4_src": "p4src.p4", "pcap_dump": true, "pcap_dir": "/home/p4/projekt/network_telemetry/src/pcap", "log_enabled": true, "log_dir": "/home/p4/projekt/network_telemetry/src/log", "cls": null, "cli_input": "s2-commands.txt", "isP4Switch": true, "isSwitch": true, "device_id": 2, "thrift_port": 9091, "json_path": "/home/p4/projekt/network_telemetry/src/p4src.json", "id": "s2"}, {"p4_src": "p4src.p4", "pcap_dump": true, "pcap_dir": "/home/p4/projekt/network_telemetry/src/pcap", "log_enabled": true, "log_dir": "/home/p4/projekt/network_telemetry/src/log", "cls": null, "cli_input": "s3-commands.txt", "isP4Switch": true, "isSwitch": true, "device_id": 3, "thrift_port": 9092, "json_path": "/home/p4/projekt/network_telemetry/src/p4src.json", "id": "s3"}, {"p4_src": "p4src.p4", "pcap_dump": true, "pcap_dir": "/home/p4/projekt/network_telemetry/src/pcap", "log_enabled": true, "log_dir": "/home/p4/projekt/network_telemetry/src/log", "cls": null, "cli_input": "s4-commands.txt", "isP4Switch": true, "isSwitch": true, "device_id": 4, "thrift_port": 9093, "json_path": "/home/p4/projekt/network_telemetry/src/p4src.json", "id": "s4"}, {"p4_src": "p4src.p4", "pcap_dump": true, "pcap_dir": "/home/p4/projekt/network_telemetry/src/pcap", "log_enabled": true, "log_dir": "/home/p4/projekt/network_telemetry/src/log", "cls": null, "cli_input": "s5-commands.txt", "isP4Switch": true, "isSwitch": true, "device_id": 5, "thrift_port": 9094, "json_path": "/home/p4/projekt/network_telemetry/src/p4src.json", "id": "s5"}, {"p4_src": "p4src.p4", "pcap_dump": true, "pcap_dir": "/home/p4/projekt/network_telemetry/src/pcap", "log_enabled": true, "log_dir": "/home/p4/projekt/network_telemetry/src/log", "cls": null, "cli_input": "s6-commands.txt", "isP4Switch": true, "isSwitch": true, "device_id": 6, "thrift_port": 9095, "json_path": "/home/p4/projekt/network_telemetry/src/p4src.json", "id": "s6"}], "links": [{"cls": null, "weight": 1, "addr2": "00:00:0a:00:00:01", "addr1": "00:01:0a:00:00:01", "intfName1": "s1-eth3", "intfName2": "h1-eth1", "node1": "s1", "node2": "h1", "port1": 3, "port2": 1, "ip2": "10.0.0.1/16", "source": "h1", "target": "s1"}, {"cls": null, "weight": 1, "addr2": "00:00:0a:00:00:02", "addr1": "00:01:0a:00:00:02", "intfName1": "s4-eth3", "intfName2": "h2-eth1", "node1": "s4", "node2": "h2", "port1": 3, "port2": 1, "ip2": "10.0.0.2/16", "source": "h2", "target": "s4"}, {"cls": null, "weight": 1, "intfName1": "s1-eth1", "intfName2": "s2-eth1", "addr1": "b2:41:6e:ce:d3:6e", "addr2": "de:91:95:ff:a1:47", "node1": "s1", "node2": "s2", "port1": 1, "port2": 1, "source": "s1", "target": "s2"}, {"cls": null, "weight": 1, "intfName1": "s1-eth2", "intfName2": "s6-eth1", "addr1": "46:a4:32:c7:9b:dc", "addr2": "32:0c:fa:c8:20:ae", "node1": "s1", "node2": "s6", "port1": 2, "port2": 1, "source": "s1", "target": "s6"}, {"cls": null, "weight": 1, "intfName1": "s2-eth4", "intfName2": "s3-eth1", "addr1": "1a:70:f0:ff:cc:3a", "addr2": "de:d6:0c:4b:b8:5e", "node1": "s2", "node2": "s3", "port1": 4, "port2": 1, "source": "s2", "target": "s3"}, {"cls": null, "weight": 1, "intfName1": "s5-eth2", "intfName2": "s2-eth3", "addr1": "12:18:79:5c:be:55", "addr2": "42:d5:04:c1:c2:b0", "node1": "s5", "node2": "s2", "port1": 2, "port2": 3, "source": "s2", "target": "s5"}, {"cls": null, "weight": 1, "intfName1": "s6-eth2", "intfName2": "s2-eth2", "addr1": "aa:13:2b:6d:bb:ab", "addr2": "4e:fc:57:d5:bc:86", "node1": "s6", "node2": "s2", "port1": 2, "port2": 2, "source": "s2", "target": "s6"}, {"cls": null, "weight": 1, "intfName1": "s3-eth4", "intfName2": "s4-eth2", "addr1": "46:fb:53:ef:4c:25", "addr2": "06:88:29:e6:3e:bf", "node1": "s3", "node2": "s4", "port1": 4, "port2": 2, "source": "s3", "target": "s4"}, {"cls": null, "weight": 1, "intfName1": "s5-eth3", "intfName2": "s3-eth3", "addr1": "2a:49:a6:99:80:cd", "addr2": "92:b5:94:12:83:ef", "node1": "s5", "node2": "s3", "port1": 3, "port2": 3, "source": "s3", "target": "s5"}, {"cls": null, "weight": 1, "intfName1": "s6-eth3", "intfName2": "s3-eth2", "addr1": "92:f0:8a:e9:97:ba", "addr2": "7a:e1:a9:14:24:aa", "node1": "s6", "node2": "s3", "port1": 3, "port2": 2, "source": "s3", "target": "s6"}, {"cls": null, "weight": 1, "intfName1": "s5-eth4", "intfName2": "s4-eth1", "addr1": "36:c1:ac:4c:3f:9e", "addr2": "26:f2:df:78:d6:ff", "node1": "s5", "node2": "s4", "port1": 4, "port2": 1, "source": "s4", "target": "s5"}, {"cls": null, "weight": 1, "intfName1": "s6-eth4", "intfName2": "s5-eth1", "addr1": "32:44:39:32:40:e6", "addr2": "7e:c6:52:9d:19:87", "node1": "s6", "node2": "s5", "port1": 4, "port2": 1, "source": "s5", "target": "s6"}]}